caustics/__init__.py
caustics/_version.py
caustics/angle_mixin.py
caustics/constants.py
caustics/func.py
caustics/tests.py
caustics/utils.py
caustics/cosmology/FlatLambdaCDM.py
caustics/cosmology/__init__.py
caustics/cosmology/base.py
caustics/lenses/__init__.py
caustics/lenses/base.py
caustics/lenses/batchedplane.py
caustics/lenses/enclosed_mass.py
caustics/lenses/epl.py
caustics/lenses/external_shear.py
caustics/lenses/mass_sheet.py
caustics/lenses/multiplane.py
caustics/lenses/multipole.py
caustics/lenses/nfw.py
caustics/lenses/pixelated_convergence.py
caustics/lenses/pixelated_deflection.py
caustics/lenses/pixelated_potential.py
caustics/lenses/point.py
caustics/lenses/pseudo_jaffe.py
caustics/lenses/sie.py
caustics/lenses/singleplane.py
caustics/lenses/sis.py
caustics/lenses/tnfw.py
caustics/lenses/utils.py
caustics/lenses/func/__init__.py
caustics/lenses/func/base.py
caustics/lenses/func/enclosed_mass.py
caustics/lenses/func/epl.py
caustics/lenses/func/external_shear.py
caustics/lenses/func/mass_sheet.py
caustics/lenses/func/multipole.py
caustics/lenses/func/nfw.py
caustics/lenses/func/pixelated_convergence.py
caustics/lenses/func/point.py
caustics/lenses/func/pseudo_jaffe.py
caustics/lenses/func/sie.py
caustics/lenses/func/sis.py
caustics/lenses/func/tnfw.py
caustics/light/__init__.py
caustics/light/base.py
caustics/light/light_stack.py
caustics/light/pixelated.py
caustics/light/pixelated_time.py
caustics/light/sersic.py
caustics/light/star_source.py
caustics/light/func/__init__.py
caustics/light/func/sersic.py
caustics/light/func/star_source.py
caustics/sims/__init__.py
caustics/sims/lens_source.py
caustics/sims/microlens.py
caustics/sims/simulator.py
caustics-1.5.2.dist-info/METADATA
caustics-1.5.2.dist-info/WHEEL
caustics-1.5.2.dist-info/licenses/LICENSE
caustics-1.5.2.dist-info/RECORD
