Metadata-Version: 2.4
Name: caustics
Version: 1.5.2
Summary: The lensing pipeline of the future: GPU-accelerated, automatically-differentiable, highly modular. Currently under heavy development: expect interface changes and some imprecise/untested calculations.
Project-URL: Homepage, https://mila.quebec/en/
Project-URL: Documentation, https://caustics.readthedocs.io/en/latest/
Project-URL: Repository, https://github.com/Ciela-Institute/caustics
Project-URL: Issues, https://github.com/Ciela-Institute/caustics/issues
Author-email: Connor Stone <connor.stone@mila.quebec>, Alexandre Adam <alexandre.adam@mila.quebec>, UW SSEC <ssec@uw.edu>
License: MIT License
License-File: LICENSE
Keywords: astronomy,astrophysics,caustics,differentiable programming,gravitational lensing,lensing,pytorch,strong lensing
Classifier: Development Status :: 1 - Planning
Classifier: Intended Audience :: Science/Research
Classifier: License :: OSI Approved :: MIT License
Classifier: Operating System :: OS Independent
Classifier: Programming Language :: Python :: 3
Requires-Python: >=3.9
Requires-Dist: astropy<7.0.0,>=6.0.0
Requires-Dist: caskade>=0.9.0
Requires-Dist: graphviz==0.20.1
Requires-Dist: h5py>=3.8.0
Requires-Dist: mpmath<1.4.0,>=1.3.0
Requires-Dist: numpy>=1.23.5
Requires-Dist: safetensors>=0.4.1
Requires-Dist: scipy>=1.8.0
Requires-Dist: torch>=2.0.0
Provides-Extra: dev
Requires-Dist: ipywidgets; extra == 'dev'
Requires-Dist: lenstronomy>1.13.0; extra == 'dev'
Requires-Dist: matplotlib; extra == 'dev'
Requires-Dist: nbconvert; extra == 'dev'
Requires-Dist: numba>=0.58.1; extra == 'dev'
Requires-Dist: pre-commit<4,>=3.6; extra == 'dev'
Requires-Dist: pyro-ppl; extra == 'dev'
Requires-Dist: pytest-cov<5,>=4.1; extra == 'dev'
Requires-Dist: pytest-mock<4,>=3.12; extra == 'dev'
Requires-Dist: pytest<9,>=8.0; extra == 'dev'
